lib_agents/__init__.py
lib_agents/fast_streaming_agent_root/__init__.py
lib_agents/fast_streaming_agent_root/agent_config.py
lib_agents/fast_streaming_agent_root/code_apply.py
lib_agents/fast_streaming_agent_root/code_block_utils.py
lib_agents/fast_streaming_agent_root/code_storage.py
lib_agents/fast_streaming_agent_root/colors.py
lib_agents/fast_streaming_agent_root/config_resolver.py
lib_agents/fast_streaming_agent_root/custom_print.py
lib_agents/fast_streaming_agent_root/dataframe_loader.py
lib_agents/fast_streaming_agent_root/dataset_usage.py
lib_agents/fast_streaming_agent_root/dutch_step_ui.py
lib_agents/fast_streaming_agent_root/embed_utils.py
lib_agents/fast_streaming_agent_root/error_collapse.py
lib_agents/fast_streaming_agent_root/forking.py
lib_agents/fast_streaming_agent_root/function_loader.py
lib_agents/fast_streaming_agent_root/function_wrapper.py
lib_agents/fast_streaming_agent_root/main.py
lib_agents/fast_streaming_agent_root/pandas_type_guard.py
lib_agents/fast_streaming_agent_root/pre_action_loader.py
lib_agents/fast_streaming_agent_root/preload.py
lib_agents/fast_streaming_agent_root/preloaded_state.py
lib_agents/fast_streaming_agent_root/search_usage.py
lib_agents/fast_streaming_agent_root/second_step_primer.py
lib_agents/fast_streaming_agent_root/semantic_layer_runtime.py
lib_agents/fast_streaming_agent_root/state_serialization.py
lib_agents/fast_streaming_agent_root/step_describer.py
lib_agents/fast_streaming_agent_root/step_state.py
lib_agents/fast_streaming_agent_root/stop_helpers.py
lib_agents/fast_streaming_agent_root/stream_inspector.py
lib_agents/fast_streaming_agent_root/stream_replacer.py
lib_agents/fast_streaming_agent_root/suggestions.py
lib_agents/fast_streaming_agent_root/table_registry.py
lib_agents/fast_streaming_agent_root/text_utils.py
lib_agents/fast_streaming_agent_root/token_guard.py
lib_agents/fast_streaming_agent_root/token_helpers.py
lib_agents/fast_streaming_agent_root/ui_helpers.py
pitchai_gpt-0.2.0.dist-info/METADATA
pitchai_gpt-0.2.0.dist-info/WHEEL
pitchai_gpt-0.2.0.dist-info/RECORD
