Metadata-Version: 2.4
Name: pitchai-gpt
Version: 0.2.0
Summary: Async GPT helpers and the Fast Streaming Agent runtime used across AFASAsk projects.
Project-URL: Homepage, https://github.com/pitchai
Project-URL: Source, https://github.com/pitchai/afas_worktree
Author: PitchAI
License: Proprietary
Keywords: agents,fastapi,gemini,gpt,llm
Classifier: Intended Audience :: Developers
Classifier: License :: Other/Proprietary License
Classifier: Operating System :: OS Independent
Classifier: Programming Language :: Python :: 3
Classifier: Programming Language :: Python :: 3.11
Requires-Python: >=3.11
Requires-Dist: boto3>=1.34
Requires-Dist: dill>=0.3.7
Requires-Dist: fastapi>=0.110
Requires-Dist: httpx>=0.27
Requires-Dist: jinja2>=3.1
Requires-Dist: numpy>=1.26
Requires-Dist: openai>=1.0.0
Requires-Dist: pandas>=2.0
Requires-Dist: polars>=0.20
Requires-Dist: pydantic>=1.10
Requires-Dist: python-dotenv>=1.0.0
Requires-Dist: pyyaml>=6.0
Requires-Dist: restrictedpython>=7.0
Requires-Dist: rich>=13.7
Requires-Dist: sqlalchemy>=2.0
Requires-Dist: tiktoken>=0.7
